stage_testing/__init__.py
stage_testing/bootstrap.py
stage_testing-0.0.4.dist-info/METADATA
stage_testing-0.0.4.dist-info/WHEEL
stage_testing-0.0.4.dist-info/top_level.txt
stage_testing-0.0.4.dist-info/RECORD
