Metadata-Version: 2.1
Name: stage-testing
Version: 0.0.4
Summary: Application context and related stuff
Home-page: https://bitbucket.org/karzade/pkscan-web3-1
Author: Sumit
Author-email: sumit.s@karza.in
License: UNKNOWN
Platform: UNKNOWN
